logger/__init__.py
logger/logger.py
zsx_pack-1.0.10.dist-info/licenses/LICENSE.txt
zsx_pack-1.0.10.dist-info/METADATA
zsx_pack-1.0.10.dist-info/WHEEL
zsx_pack-1.0.10.dist-info/top_level.txt
zsx_pack-1.0.10.dist-info/RECORD
