Metadata-Version: 2.4
Name: zsx_pack
Version: 1.0.10
Summary: 自用包，主要是为了logger无法屏蔽第三方包日志而开发的
Home-page: https://github.com/ziyueguyi/zsx_pack
Author: zsx
Author-email: 17630583910@163.com
Maintainer: zsx
Maintainer-email: 17630583910@163.com
License: MIT
Project-URL: Bug Tracker, https://github.com/ziyueguyi/zsx_pack
Platform: Windows
Platform: Linux
Classifier: Development Status :: 3 - Alpha
Classifier: Intended Audience :: Developers
Classifier: Topic :: Software Development :: Build Tools
Classifier: License :: OSI Approved :: MIT License
Classifier: Natural Language :: Chinese (Simplified)
Classifier: Programming Language :: Python :: 3
Requires-Python: >=3.6
License-File: LICENSE.txt
Requires-Dist: colorama>=0.4.6
Dynamic: author
Dynamic: author-email
Dynamic: classifier
Dynamic: description
Dynamic: description-content-type
Dynamic: home-page
Dynamic: license
Dynamic: license-file
Dynamic: maintainer
Dynamic: maintainer-email
Dynamic: platform
Dynamic: project-url
Dynamic: requires-dist
Dynamic: requires-python
Dynamic: summary
